LICENSE
README.md
setup.py
ceasylog/Logger.py
ceasylog/LoggerConfiger.py
ceasylog/LoggerLevel.py
ceasylog/LoggerNetworkConfiger.py
ceasylog/LoggerStatic.py
ceasylog/__init__.py
ceasylog.egg-info/PKG-INFO
ceasylog.egg-info/SOURCES.txt
ceasylog.egg-info/dependency_links.txt
ceasylog.egg-info/requires.txt
ceasylog.egg-info/top_level.txt